brutus/PSMrLF_lnprior.dat
brutus/__init__.py
brutus/cluster.py
brutus/dust.py
brutus/filters.py
brutus/fitting.py
brutus/los.py
brutus/pdf.py
brutus/plotting.py
brutus/seds.py
brutus/utils.py
astro_brutus-0.8.2.dist-info/AUTHORS.md
astro_brutus-0.8.2.dist-info/LICENSE
astro_brutus-0.8.2.dist-info/METADATA
astro_brutus-0.8.2.dist-info/WHEEL
astro_brutus-0.8.2.dist-info/top_level.txt
astro_brutus-0.8.2.dist-info/RECORD
