Metadata-Version: 2.1
Name: astro-brutus
Version: 0.8.2
Summary: Brute-force Bayesian inference for photometric distances, reddenings, and stellar properties
Home-page: https://github.com/joshspeagle/brutus
Author: Joshua S Speagle
Author-email: jspeagle@cfa.harvard.edu
License: MIT
Keywords: brute force,photometry,bayesian,stellar,star,cluster,isochrone,dust,reddening,parallax,distance,template fitting
Platform: UNKNOWN
Classifier: Development Status :: 4 - Beta
Classifier: License :: OSI Approved :: MIT License
Classifier: Natural Language :: English
Classifier: Programming Language :: Python :: 2.7
Classifier: Programming Language :: Python :: 3.6
Classifier: Operating System :: OS Independent
Classifier: Topic :: Scientific/Engineering :: Astronomy
Classifier: Intended Audience :: Science/Research
Requires-Dist: numpy
Requires-Dist: scipy
Requires-Dist: matplotlib
Requires-Dist: six
Requires-Dist: h5py
Requires-Dist: healpy
Requires-Dist: numba
